LICENSE
MANIFEST.in
README.md
requirements.txt
setup.py
pygenerator3/PYGENERATOR3_VERSION
pygenerator3/__init__.py
pygenerator3/args.py
pygenerator3/package_generator.py
pygenerator3.egg-info/PKG-INFO
pygenerator3.egg-info/SOURCES.txt
pygenerator3.egg-info/dependency_links.txt
pygenerator3.egg-info/requires.txt
pygenerator3.egg-info/top_level.txt
pygenerator3/scripts/package-generator
pygenerator3/templates/.gitignore.template
pygenerator3/templates/MANIFEST.in.template
pygenerator3/templates/README.md.template
pygenerator3/templates/requirements.txt.template
pygenerator3/templates/setup.py.template
pygenerator3/templates/package/__init__.py