Metadata-Version: 2.1
Name: pygenerator3
Version: 0.0.2
Summary: Python Package Generator
Home-page: https://gitlab.com/shlomi.ben.david/pygenerator3
Author: Shlomi Ben-David
Author-email: shlomi.ben.david@gmail.com
License: UNKNOWN
Platform: UNKNOWN
Classifier: Programming Language :: Python :: 3.5
Classifier: License :: OSI Approved :: MIT License
Classifier: Operating System :: OS Independent
Requires-Python: >=3.5
